Metadata-Version: 2.4
Name: rshogi-py-avx2
Version: 0.2.0
Classifier: Programming Language :: Python :: 3
Classifier: Programming Language :: Rust
Classifier: License :: OSI Approved :: MIT License
Classifier: Operating System :: OS Independent
License-File: LICENSE
Summary: Python bindings for the rshogi core library (AVX2 build).
Author: rshogi contributors
Requires-Python: >=3.9
Project-URL: Repository, https://github.com/nyoki-mtl/rshogi
